{"select":{},"input":{"spouseSelection1237697":{"seccion":null,"hubspotProperty":""},"spouseFamilyName1237698":{"seccion":null,"hubspotProperty":""},"spouseGiven1237699":{"seccion":null,"hubspotProperty":""},"spouseBirthDate1237700":{"seccion":"Enter the date as YYYY-MM-DD, or click the down arrow to open the calendar.","hubspotProperty":""},"yourFamilyName1237701":{"seccion":null,"hubspotProperty":""},"yourGivenName1237702":{"seccion":null,"hubspotProperty":""},"twoYou1237703":{"seccion":null,"hubspotProperty":""},"numberPersons1237704":{"seccion":null,"hubspotProperty":""},"numberPersonsPreviousSignedStill1237705":{"seccion":null,"hubspotProperty":""},"numberPersonsPreviousSignedNotYet1237706":{"seccion":null,"hubspotProperty":""},"numberPersonsPreviousCosignedStill1237707":{"seccion":null,"hubspotProperty":""},"numberPersonsPreviousCosignedNotYet1237708":{"seccion":null,"hubspotProperty":""},"spouseNumPersPrevsignedStill1237709":{"seccion":null,"hubspotProperty":""},"spouseNumPersPrevsignedNotYet1237710":{"seccion":null,"hubspotProperty":""},"spouseNumPersPrevCosignedStill1237711":{"seccion":null,"hubspotProperty":""},"spouseNumPersPrevCosignedNotYet1237712":{"seccion":null,"hubspotProperty":""},"fiveSpouseCount1237713":{"seccion":null,"hubspotProperty":""},"sixFamilyMember1237714":{"seccion":null,"hubspotProperty":""},"totalNumberPersons1237716":{"seccion":null,"hubspotProperty":""},"spouseSelection1237718":{"seccion":null,"hubspotProperty":""},"sponsorSOCsin1237719":{"seccion":"Please enter the 9 digit S.I.N. number. The number will be displayed as: XXX-XXX-XXX.","hubspotProperty":""},"sponsorSOCdate1237721":{"seccion":"Enter the date as YYYY-MM-DD, or click the down arrow to open the calendar.","hubspotProperty":""},"threeBiFamilyName1237723":{"seccion":"Family name","hubspotProperty":""},"threeBiGivenName1237724":{"seccion":"Given name(s)","hubspotProperty":""},"threeBiFamilyName1237725":{"seccion":"Family name","hubspotProperty":""},"threeBiGivenName1237726":{"seccion":"Given name(s)","hubspotProperty":""},"threeBiFamilyName1237727":{"seccion":"Family name","hubspotProperty":""},"threeBiGivenName1237728":{"seccion":"Given name(s)","hubspotProperty":""},"threeBiiFamilyName1237729":{"seccion":"Family name","hubspotProperty":""},"threeBiiGivenName1237730":{"seccion":"Given name(s)","hubspotProperty":""},"threeBiiFamilyName1237731":{"seccion":"Family name","hubspotProperty":""},"threeBiiGivenName1237732":{"seccion":"Given name(s)","hubspotProperty":""},"threeBiiFamilyName1237733":{"seccion":"Family name","hubspotProperty":""},"threeBiiGivenName1237734":{"seccion":"Given name(s)","hubspotProperty":""},"threeBiiiFamilyName1237735":{"seccion":"Family name","hubspotProperty":""},"threeBiiiGivenName1237736":{"seccion":"Given name(s)","hubspotProperty":""},"threeBiiiFamilyName1237737":{"seccion":"Family name","hubspotProperty":""},"threeBiiiGivenName1237738":{"seccion":"Given name(s)","hubspotProperty":""},"threeBiiiFamilyName1237739":{"seccion":"Family name","hubspotProperty":""},"threeBiiiGivenName1237740":{"seccion":"Given name(s)","hubspotProperty":""},"threeBivFamilyName1237741":{"seccion":"Family name","hubspotProperty":""},"threeBivGivenName1237742":{"seccion":"Given name(s)","hubspotProperty":""},"threeBivFamilyName1237743":{"seccion":"Family name","hubspotProperty":""},"threeBivGivenName1237744":{"seccion":"Given name(s)","hubspotProperty":""},"threeBivFamilyName1237745":{"seccion":"Family name","hubspotProperty":""},"threeBivGivenName1237746":{"seccion":"Given name(s)","hubspotProperty":""},"threeBivBirthDatte1237747":{"seccion":"Date of birth (YYYY-MM-DD)","hubspotProperty":""},"threeBivBirthDatte1237748":{"seccion":"Date of birth (YYYY-MM-DD)","hubspotProperty":""},"threeBivBirthDatte1237749":{"seccion":"Date of birth (YYYY-MM-DD)","hubspotProperty":""},"threeBiiiBirthDatte1237750":{"seccion":"Date of birth (YYYY-MM-DD)","hubspotProperty":""},"threeBiiiBirthDatte1237751":{"seccion":"Date of birth (YYYY-MM-DD)","hubspotProperty":""},"threeBiiiBirthDatte1237752":{"seccion":"Date of birth (YYYY-MM-DD)","hubspotProperty":""},"threeBiiBirthDatte1237753":{"seccion":"Date of birth (YYYY-MM-DD)","hubspotProperty":""},"threeBiiBirthDatte1237754":{"seccion":"Date of birth (YYYY-MM-DD)","hubspotProperty":""},"threeBiiBirthDatte1237755":{"seccion":"Date of birth (YYYY-MM-DD)","hubspotProperty":""},"threeBiBirthDatte1237756":{"seccion":"Date of birth (YYYY-MM-DD)","hubspotProperty":""},"threeBiBirthDatte1237757":{"seccion":"Date of birth (YYYY-MM-DD)","hubspotProperty":""},"threeBiBirthDatte1237758":{"seccion":"Date of birth (YYYY-MM-DD)","hubspotProperty":""},"fouriFamilyName1237760":{"seccion":"Family name","hubspotProperty":""},"fouriGivenName1237761":{"seccion":"Given name(s)","hubspotProperty":""},"fouriFamilyName1237762":{"seccion":"Family name","hubspotProperty":""},"fouriGivenName1237763":{"seccion":"Given name(s)","hubspotProperty":""},"fouriFamilyName1237764":{"seccion":"Family name","hubspotProperty":""},"fouriGivenName1237765":{"seccion":"Given name(s)","hubspotProperty":""},"fouriiFamilyName1237766":{"seccion":"Family name","hubspotProperty":""},"fouriiGivenName1237767":{"seccion":"Given name(s)","hubspotProperty":""},"fouriiFamilyName1237768":{"seccion":"Family name","hubspotProperty":""},"fouriiGivenName1237769":{"seccion":"Given name(s)","hubspotProperty":""},"fouriiBirthDate1237770":{"seccion":"Date of birth (YYYY-MM-DD)","hubspotProperty":""},"fouriiFamilyName1237771":{"seccion":"Family name","hubspotProperty":""},"fouriiGivenName1237772":{"seccion":"Given name(s)","hubspotProperty":""},"fouriiBirthDate1237773":{"seccion":"Date of birth (YYYY-MM-DD)","hubspotProperty":""},"fouriiiFamilyName1237774":{"seccion":"Family name","hubspotProperty":""},"fouriiiGivenName1237775":{"seccion":"Given name(s)","hubspotProperty":""},"fouriiiBirthDate1237776":{"seccion":"Date of birth (YYYY-MM-DD)","hubspotProperty":""},"fouriiiFamilyName1237777":{"seccion":"Family name","hubspotProperty":""},"fouriiiGivenName1237778":{"seccion":"Given name(s)","hubspotProperty":""},"fouriiiBirthDate1237779":{"seccion":"Date of birth (YYYY-MM-DD)","hubspotProperty":""},"fouriiiFamilyName1237780":{"seccion":"Family name","hubspotProperty":""},"fouriiiGivenName1237781":{"seccion":"Given name(s)","hubspotProperty":""},"fouriiiBirthDate1237782":{"seccion":"Date of birth (YYYY-MM-DD)","hubspotProperty":""},"fouriiBirthDate1237783":{"seccion":"Date of birth (YYYY-MM-DD)","hubspotProperty":""},"fouriBirthDate1237784":{"seccion":"Date of birth (YYYY-MM-DD)","hubspotProperty":""},"fouriBirthDate1237785":{"seccion":"Date of birth (YYYY-MM-DD)","hubspotProperty":""},"fouriBirthDate1237786":{"seccion":"Date of birth (YYYY-MM-DD)","hubspotProperty":""},"fourivFamilyName1237788":{"seccion":"Family name","hubspotProperty":""},"fourivGivenName1237789":{"seccion":"Given name(s)","hubspotProperty":""},"fourivBirthDate1237790":{"seccion":"Date of birth (YYYY-MM-DD)","hubspotProperty":""},"fourivFamilyName1237791":{"seccion":"Family name","hubspotProperty":""},"fourivGivenName1237792":{"seccion":"Given name(s)","hubspotProperty":""},"fourivBirthDate1237793":{"seccion":"Date of birth (YYYY-MM-DD)","hubspotProperty":""},"fourivFamilyName1237794":{"seccion":"Family name","hubspotProperty":""},"fourivGivenName1237795":{"seccion":"Given name(s)","hubspotProperty":""},"fourivBirthDate1237796":{"seccion":"Date of birth (YYYY-MM-DD)","hubspotProperty":""},"fiveFamilyName1237798":{"seccion":"Family name","hubspotProperty":""},"fiveGivenName1237799":{"seccion":"Given name(s)","hubspotProperty":""},"fiveBrithDate1237800":{"seccion":"Date of birth (YYYY-MM-DD)","hubspotProperty":""},"sixFamilyName1237802":{"seccion":"Family name","hubspotProperty":""},"sixGivenName1237803":{"seccion":"Given name(s)","hubspotProperty":""},"sixBirthDate1237804":{"seccion":"Date of birth (YYYY-MM-DD)","hubspotProperty":""},"sixFamilyName1237805":{"seccion":"Family name","hubspotProperty":""},"sixGivenName1237806":{"seccion":"Given name(s)","hubspotProperty":""},"sixBirthDate1237807":{"seccion":"Date of birth (YYYY-MM-DD)","hubspotProperty":""},"sixFamilyName1237808":{"seccion":"Family name","hubspotProperty":""},"sixGivenName1237809":{"seccion":"Given name(s)","hubspotProperty":""},"sixBirthDate1237810":{"seccion":"Date of birth (YYYY-MM-DD)","hubspotProperty":""},"unemployed1237812":{"seccion":null,"hubspotProperty":""},"employed1237814":{"seccion":null,"hubspotProperty":""},"selfEmployed1237815":{"seccion":null,"hubspotProperty":""},"currentDate1237820":{"seccion":"Date From (YYYY-MM-DD)","hubspotProperty":""},"field1241013":{"seccion":"Phone no.","hubspotProperty":""},"NumericField11237823":{"seccion":"Gross income/Benefits for period","hubspotProperty":""},"TextField21237824":{"seccion":"Family size","hubspotProperty":""},"currentDate1237826":{"seccion":"Date From (YYYY-MM-DD)","hubspotProperty":""},"currentDate1237827":{"seccion":"Date to (YYYY-MM-DD)","hubspotProperty":""},"field1241146":{"seccion":"Phone no.","hubspotProperty":""},"NumericField11237830":{"seccion":"Gross income/Benefits for period","hubspotProperty":""},"TextField21237831":{"seccion":"Family size","hubspotProperty":""},"currentDate1237833":{"seccion":"Date From (YYYY-MM-DD)","hubspotProperty":""},"currentDate1237834":{"seccion":"Date to (YYYY-MM-DD)","hubspotProperty":""},"field1241279":{"seccion":"Phone no.","hubspotProperty":""},"NumericField11237837":{"seccion":"Gross income/Benefits for period","hubspotProperty":""},"TextField21237838":{"seccion":"Family size","hubspotProperty":""},"currentDate1237840":{"seccion":"Date From (YYYY-MM-DD)","hubspotProperty":""},"currentDate1237841":{"seccion":"Date to (YYYY-MM-DD)","hubspotProperty":""},"field1241412":{"seccion":"Phone no.","hubspotProperty":""},"NumericField11237844":{"seccion":"Gross income/Benefits for period","hubspotProperty":""},"TextField21237845":{"seccion":"Family size","hubspotProperty":""},"currentDate1237847":{"seccion":"Date From (YYYY-MM-DD)","hubspotProperty":""},"currentDate1237848":{"seccion":"Date to (YYYY-MM-DD)","hubspotProperty":""},"field1241545":{"seccion":"Phone no.","hubspotProperty":""},"NumericField11237851":{"seccion":"Gross income/Benefits for period","hubspotProperty":""},"TextField21237852":{"seccion":"Family size","hubspotProperty":""},"currentDate1237854":{"seccion":"Date From (YYYY-MM-DD)","hubspotProperty":""},"currentDate1237855":{"seccion":"Date to (YYYY-MM-DD)","hubspotProperty":""},"field1241678":{"seccion":"Phone no.","hubspotProperty":""},"NumericField11237858":{"seccion":"Gross income/Benefits for period","hubspotProperty":""},"TextField21237859":{"seccion":"Family size","hubspotProperty":""},"currentDate1237861":{"seccion":"Date From (YYYY-MM-DD)","hubspotProperty":""},"currentDate1237862":{"seccion":"Date to (YYYY-MM-DD)","hubspotProperty":""},"field1241811":{"seccion":"Phone no.","hubspotProperty":""},"NumericField11237865":{"seccion":"Gross income/Benefits for period","hubspotProperty":""},"TextField21237866":{"seccion":"Family size","hubspotProperty":""},"currentDate1237868":{"seccion":"Date From (YYYY-MM-DD)","hubspotProperty":""},"currentDate1237869":{"seccion":"Date to (YYYY-MM-DD)","hubspotProperty":""},"field1241944":{"seccion":"Phone no.","hubspotProperty":""},"NumericField11237872":{"seccion":"Gross income/Benefits for period","hubspotProperty":""},"TextField21237873":{"seccion":"Family size","hubspotProperty":""},"currentDate1237875":{"seccion":"Date From (YYYY-MM-DD)","hubspotProperty":""},"currentDate1237876":{"seccion":"Date to (YYYY-MM-DD)","hubspotProperty":""},"field1242077":{"seccion":"Phone no.","hubspotProperty":""},"NumericField11237879":{"seccion":"Gross income/Benefits for period","hubspotProperty":""},"TextField21237880":{"seccion":"Family size","hubspotProperty":""},"currentDate1237882":{"seccion":"Date From (YYYY-MM-DD)","hubspotProperty":""},"currentDate1237883":{"seccion":"Date to (YYYY-MM-DD)","hubspotProperty":""},"field1242210":{"seccion":"Phone no.","hubspotProperty":""},"NumericField11237886":{"seccion":"Gross income/Benefits for period","hubspotProperty":""},"TextField21237887":{"seccion":"Family size","hubspotProperty":""},"currentDate1237889":{"seccion":"Date From (YYYY-MM-DD)","hubspotProperty":""},"currentDate1237890":{"seccion":"Date to (YYYY-MM-DD)","hubspotProperty":""},"field1242343":{"seccion":"Phone no.","hubspotProperty":""},"NumericField11237893":{"seccion":"Gross income/Benefits for period","hubspotProperty":""},"TextField21237894":{"seccion":"Family size","hubspotProperty":""},"field1242465":{"seccion":"Check box must be checked when you have enclosed...","hubspotProperty":""},"employed1237896":{"seccion":null,"hubspotProperty":""},"selfEmployed1237897":{"seccion":null,"hubspotProperty":""},"spouseSelection1237900":{"seccion":null,"hubspotProperty":""},"sponsorSOCsin1237901":{"seccion":"Please enter the 9 digit S.I.N. number. The number will be displayed as: XXX-XXX-XXX.","hubspotProperty":""},"sponsorSOCdate1237903":{"seccion":"Enter the date as YYYY-MM-DD, or click the down arrow to open the calendar.","hubspotProperty":""},"currentDate1237908":{"seccion":"Date From (YYYY-MM-DD)","hubspotProperty":""},"field1242851":{"seccion":"Phone no.","hubspotProperty":""},"NumericField11237911":{"seccion":"Gross income/Benefits for period","hubspotProperty":""},"TextField21237912":{"seccion":"Family size","hubspotProperty":""},"currentDate1237914":{"seccion":"Date From (YYYY-MM-DD)","hubspotProperty":""},"currentDate1237915":{"seccion":"Date To (YYYY-MM-DD)","hubspotProperty":""},"field1242984":{"seccion":"Phone no.","hubspotProperty":""},"NumericField11237918":{"seccion":"Gross income/Benefits for period","hubspotProperty":""},"TextField21237919":{"seccion":"Family size","hubspotProperty":""},"currentDate1237921":{"seccion":"Date From (YYYY-MM-DD)","hubspotProperty":""},"currentDate1237922":{"seccion":"Date To (YYYY-MM-DD)","hubspotProperty":""},"field1243117":{"seccion":"Phone no.","hubspotProperty":""},"NumericField11237925":{"seccion":"Gross income/Benefits for period","hubspotProperty":""},"TextField21237926":{"seccion":"Family size","hubspotProperty":""},"currentDate1237928":{"seccion":"Date From (YYYY-MM-DD)","hubspotProperty":""},"currentDate1237929":{"seccion":"Date To (YYYY-MM-DD)","hubspotProperty":""},"field1243250":{"seccion":"Phone no.","hubspotProperty":""},"NumericField11237932":{"seccion":"Gross income/Benefits for period","hubspotProperty":""},"TextField21237933":{"seccion":"Family size","hubspotProperty":""},"currentDate1237935":{"seccion":"Date From (YYYY-MM-DD)","hubspotProperty":""},"currentDate1237936":{"seccion":"Date To (YYYY-MM-DD)","hubspotProperty":""},"field1243383":{"seccion":"Phone no.","hubspotProperty":""},"NumericField11237939":{"seccion":"Gross income/Benefits for period","hubspotProperty":""},"TextField21237940":{"seccion":"Family size","hubspotProperty":""},"currentDate1237942":{"seccion":"Date From (YYYY-MM-DD)","hubspotProperty":""},"currentDate1237943":{"seccion":"Date To (YYYY-MM-DD)","hubspotProperty":""},"field1243516":{"seccion":"Phone no.","hubspotProperty":""},"NumericField11237946":{"seccion":"Gross income/Benefits for period","hubspotProperty":""},"TextField21237947":{"seccion":"Family size","hubspotProperty":""},"currentDate1237949":{"seccion":"Date From (YYYY-MM-DD)","hubspotProperty":""},"currentDate1237950":{"seccion":"Date To (YYYY-MM-DD)","hubspotProperty":""},"field1243649":{"seccion":"Phone no.","hubspotProperty":""},"NumericField11237953":{"seccion":"Gross income/Benefits for period","hubspotProperty":""},"TextField21237954":{"seccion":"Family size","hubspotProperty":""},"currentDate1237956":{"seccion":"Date From (YYYY-MM-DD)","hubspotProperty":""},"currentDate1237957":{"seccion":"Date To (YYYY-MM-DD)","hubspotProperty":""},"field1243782":{"seccion":"Phone no.","hubspotProperty":""},"NumericField11237960":{"seccion":"Gross income/Benefits for period","hubspotProperty":""},"TextField21237961":{"seccion":"Family size","hubspotProperty":""},"currentDate1237963":{"seccion":"Date From (YYYY-MM-DD)","hubspotProperty":""},"currentDate1237964":{"seccion":"Date To (YYYY-MM-DD)","hubspotProperty":""},"field1243915":{"seccion":"Phone no.","hubspotProperty":""},"NumericField11237967":{"seccion":"Gross income/Benefits for period","hubspotProperty":""},"TextField21237968":{"seccion":"Family size","hubspotProperty":""},"currentDate1237970":{"seccion":"Date From (YYYY-MM-DD)","hubspotProperty":""},"currentDate1237971":{"seccion":"Date To (YYYY-MM-DD)","hubspotProperty":""},"field1244048":{"seccion":"Phone no.","hubspotProperty":""},"NumericField11237974":{"seccion":"Gross income/Benefits for period","hubspotProperty":""},"TextField21237975":{"seccion":"Family size","hubspotProperty":""},"currentDate1237977":{"seccion":"Date From (YYYY-MM-DD)","hubspotProperty":""},"currentDate1237978":{"seccion":"Date To (YYYY-MM-DD)","hubspotProperty":""},"field1244181":{"seccion":"Phone no.","hubspotProperty":""},"NumericField11237981":{"seccion":"Gross income/Benefits for period","hubspotProperty":""},"TextField21237982":{"seccion":"Family size","hubspotProperty":""}},"textarea":{"sponsorSOCsign1237720":{"seccion":null,"hubspotProperty":""},"unemployedDetails1237813":{"seccion":"Give details of your current situation and indicate how you support yourself. If you need additional space, provide details on a separate sheet of paper.","hubspotProperty":""},"TextField21237821":{"seccion":"Employer name","hubspotProperty":""},"TextField21237822":{"seccion":"Address","hubspotProperty":""},"TextField21237828":{"seccion":"Employer name","hubspotProperty":""},"TextField21237829":{"seccion":"Address","hubspotProperty":""},"TextField21237835":{"seccion":"Employer name","hubspotProperty":""},"TextField21237836":{"seccion":"Address","hubspotProperty":""},"TextField21237842":{"seccion":"Employer name","hubspotProperty":""},"TextField21237843":{"seccion":"Address","hubspotProperty":""},"TextField21237849":{"seccion":"Employer name","hubspotProperty":""},"TextField21237850":{"seccion":"Address","hubspotProperty":""},"TextField21237856":{"seccion":"Employer name","hubspotProperty":""},"TextField21237857":{"seccion":"Address","hubspotProperty":""},"TextField21237863":{"seccion":"Employer name","hubspotProperty":""},"TextField21237864":{"seccion":"Address","hubspotProperty":""},"TextField21237870":{"seccion":"Employer name","hubspotProperty":""},"TextField21237871":{"seccion":"Address","hubspotProperty":""},"TextField21237877":{"seccion":"Employer name","hubspotProperty":""},"TextField21237878":{"seccion":"Address","hubspotProperty":""},"TextField21237884":{"seccion":"Employer name","hubspotProperty":""},"TextField21237885":{"seccion":"Address","hubspotProperty":""},"TextField21237891":{"seccion":"Employer name","hubspotProperty":""},"TextField21237892":{"seccion":"Address","hubspotProperty":""},"unemployedDetails1237898":{"seccion":null,"hubspotProperty":""},"sponsorSOCsign1237902":{"seccion":null,"hubspotProperty":""},"TextField21237909":{"seccion":"Employer name","hubspotProperty":""},"TextField21237910":{"seccion":"Address","hubspotProperty":""},"TextField21237916":{"seccion":"Employer name","hubspotProperty":""},"TextField21237917":{"seccion":"Address","hubspotProperty":""},"TextField21237923":{"seccion":"Employer name","hubspotProperty":""},"TextField21237924":{"seccion":"Address","hubspotProperty":""},"TextField21237930":{"seccion":"Employer name","hubspotProperty":""},"TextField21237931":{"seccion":"Address","hubspotProperty":""},"TextField21237937":{"seccion":"Employer name","hubspotProperty":""},"TextField21237938":{"seccion":"Address","hubspotProperty":""},"TextField21237944":{"seccion":"Employer name","hubspotProperty":""},"TextField21237945":{"seccion":"Address","hubspotProperty":""},"TextField21237951":{"seccion":"Employer name","hubspotProperty":""},"TextField21237952":{"seccion":"Address","hubspotProperty":""},"TextField21237958":{"seccion":"Employer name","hubspotProperty":""},"TextField21237959":{"seccion":"Address","hubspotProperty":""},"TextField21237965":{"seccion":"Employer name","hubspotProperty":""},"TextField21237966":{"seccion":"Address","hubspotProperty":""},"TextField21237972":{"seccion":"Employer name","hubspotProperty":""},"TextField21237973":{"seccion":"Address","hubspotProperty":""},"TextField21237979":{"seccion":"Employer name","hubspotProperty":""},"TextField21237980":{"seccion":"Address","hubspotProperty":""}}}